baike/__init__.py
baike/baike.py
baike-1.5.0.dist-info/LICENSE
baike-1.5.0.dist-info/METADATA
baike-1.5.0.dist-info/WHEEL
baike-1.5.0.dist-info/top_level.txt
baike-1.5.0.dist-info/RECORD
