Metadata-Version: 2.1
Name: baike
Version: 1.5.0
Summary: BaiduBaike search bot
Home-page: https://github.com/1MLightyears/baike
Author: Lightyears
Author-email: 1MLightyears@gmail.com
License: Apache 2.0
Platform: UNKNOWN
Classifier: Programming Language :: Python :: 3.6
Classifier: Programming Language :: Python :: 3.7
Classifier: Operating System :: OS Independent
Classifier: Development Status :: 2 - Pre-Alpha
Classifier: License :: OSI Approved :: Apache Software License
Classifier: Natural Language :: Chinese (Simplified)
Requires-Python: >=3.6
Requires-Dist: requests
Requires-Dist: lxml
